lsbsteg/__init__.py
lsbsteg-0.1.0.dist-info/LICENCE
lsbsteg-0.1.0.dist-info/METADATA
lsbsteg-0.1.0.dist-info/WHEEL
lsbsteg-0.1.0.dist-info/top_level.txt
lsbsteg-0.1.0.dist-info/RECORD
